{
    "DNDConfig": null,
    "_height_": {
        "type": "string",
        "value": "120dp"
    },
    "_left_": {
        "type": "string",
        "value": "0dp"
    },
    "_margin_": [
        0,
        0,
        0,
        0
    ],
    "_orientation_": 6,
    "_padding_": [
        0,
        0,
        0,
        0
    ],
    "_percent_": true,
    "_skin_": "s969b488b7f74b809b660be1af1189e2",
    "_top_": {
        "type": "string",
        "value": "0dp"
    },
    "_width_": {
        "type": "string",
        "value": "100%"
    },
    "allboxes": [],
    "autogrowmode": 0,
    "canUpdateUI": true,
    "children": [
        "flxProfile",
        "flxAction"
    ],
    "clipbounds": true,
    "containerId": true,
    "containerweight": 100,
    "controllerInfo": {
        "default": {
            "channel": "tablet",
            "name": "profileContainerController"
        }
    },
    "enablescrolling": true,
    "id": "profileContainer",
    "info": null,
    "isTemplate": true,
    "iscustomlayout": false,
    "isvisible": true,
    "kuid": "a70a8ee79b734a43828374cafe967ba4",
    "layouttype": 3,
    "name": "kony.ui.FlexContainer",
    "parent": "Temp0b40d1da1001a4f",
    "pf": "Temp0b40d1da1001a4f",
    "retaincontentalignment": false,
    "retainflexpositionproperties": false,
    "retainflowhorizontalalignment": false,
    "snapgridsize": 10,
    "snaptogrid": true,
    "wType": "FlexContainer",
    "widgetalignment": 1
}